{
 "hero_title": "Professional Wedding and Event Makeup & Hair Services",
"hero_button_text": "Book a Consultation",
"hero_button_link": "/inquiry.html",

"about_title": "",
"about_p1": "Hello! I am a professional makeup and hair artist offering on-location services for weddings and special events.",
"about_p2": "This work is driven by passion and attention to detail. Every look is thoughtfully created to highlight natural beauty, enhance individual features, and deliver a polished, elegant result tailored to each client."
}
